colindex2/__init__.py
colindex2/circle_overlap.py
colindex2/colindex2.py
colindex2/commands.py
colindex2/data_settings.py
colindex2/draw_map.py
colindex2/get_IDfile.py
colindex2/modules.py
colindex2/tracking_overlap2.py
colindex2-2.10.5.dist-info/licenses/LICENSE
colindex2-2.10.5.dist-info/METADATA
colindex2-2.10.5.dist-info/WHEEL
colindex2-2.10.5.dist-info/entry_points.txt
colindex2-2.10.5.dist-info/top_level.txt
colindex2-2.10.5.dist-info/RECORD
