Metadata-Version: 2.4
Name: colindex2
Version: 2.10.5
Summary: depression detection/tracking schemes
Home-page: https://gitlab.com/kasugab3621/colindex2.git
Author: Satoru Kasuga
Author-email: kasugab3621@outlook.com
License-File: LICENSE
Requires-Dist: numpy
Requires-Dist: pandas
Requires-Dist: xarray
Requires-Dist: scipy
Requires-Dist: torch
Requires-Dist: netCDF4
Requires-Dist: h5netcdf
Requires-Dist: matplotlib
Requires-Dist: cartopy
Dynamic: author
Dynamic: author-email
Dynamic: description
Dynamic: description-content-type
Dynamic: home-page
Dynamic: license-file
Dynamic: requires-dist
Dynamic: summary
